{
	"_type": "export",
	"__export_format": 4,
	"__export_date": "2026-03-15T22:50:00.000Z",
	"__export_source": "insomnia.desktop.app:v8.6.1",
	"resources": [
		{
			"_id": "wrk_mediahub_1",
			"_type": "workspace",
			"parentId": null,
			"modified": 1710340000000,
			"created": 1710340000000,
			"name": "Mediahub Microservices",
			"description": "Collection for testing the Mediahub Microservices stack through the API Gateway.",
			"scope": "collection"
		},
		{
			"_id": "env_mediahub_1",
			"_type": "environment",
			"parentId": "wrk_mediahub_1",
			"modified": 1710340000000,
			"created": 1710340000000,
			"name": "Local Development",
			"data": {
				"base_url": "http://localhost:8080",
				"eureka_url": "http://localhost:8761"
			},
			"dataPropertyOrder": {
				"&": [
					"base_url",
					"eureka_url"
				]
			},
			"color": null,
			"isPrivate": false,
			"metaSortKey": 1710340000000
		},
		{
			"_id": "fld_user_1",
			"_type": "request_group",
			"parentId": "wrk_mediahub_1",
			"modified": 1710340000000,
			"created": 1710340000000,
			"name": "User Service",
			"description": "",
			"environment": {},
			"environmentPropertyOrder": null,
			"metaSortKey": -1710340000000
		},
		{
			"_id": "req_create_user",
			"_type": "request",
			"parentId": "fld_user_1",
			"modified": 1710340000000,
			"created": 1710340000000,
			"url": "{{ _.base_url }}/api/v1/users",
			"name": "Create User",
			"description": "",
			"method": "POST",
			"body": {
				"mimeType": "application/json",
				"text": "{\n  \"firstName\": \"Manual\",\n  \"lastName\": \"Tester\",\n  \"email\": \"manual_{% now 'unix' %}@test.com\",\n  \"password\": \"password123\",\n  \"role\": \"USER\"\n}"
			},
			"parameters": [],
			"headers": [
				{
					"name": "Content-Type",
					"value": "application/json"
				}
			],
			"authentication": {},
			"metaSortKey": -1710340000000,
			"isPrivate": false,
			"settingStoreCookies": true,
			"settingSendCookies": true,
			"settingDisableRenderRequestBody": false,
			"settingEncodeUrl": true,
			"settingRebuildPath": true,
			"settingFollowRedirects": "global"
		},
		{
			"_id": "req_list_users",
			"_type": "request",
			"parentId": "fld_user_1",
			"modified": 1710340000000,
			"created": 1710340000000,
			"url": "{{ _.base_url }}/api/v1/users",
			"name": "List All Users",
			"description": "",
			"method": "GET",
			"body": {},
			"parameters": [],
			"headers": [],
			"authentication": {},
			"metaSortKey": -1710330000000,
			"isPrivate": false,
			"settingStoreCookies": true,
			"settingSendCookies": true,
			"settingDisableRenderRequestBody": false,
			"settingEncodeUrl": true,
			"settingRebuildPath": true,
			"settingFollowRedirects": "global"
		},
		{
			"_id": "fld_media_1",
			"_type": "request_group",
			"parentId": "wrk_mediahub_1",
			"modified": 1710340000000,
			"created": 1710340000000,
			"name": "Media Service",
			"description": "",
			"environment": {},
			"environmentPropertyOrder": null,
			"metaSortKey": -1710338000000
		},
		{
			"_id": "req_create_media",
			"_type": "request",
			"parentId": "fld_media_1",
			"modified": 1710340000000,
			"created": 1710340000000,
			"url": "{{ _.base_url }}/api/v1/media",
			"name": "Create Media",
			"description": "",
			"method": "POST",
			"body": {
				"mimeType": "application/json",
				"text": "{\n  \"title\": \"Interstellar\",\n  \"description\": \"Explorers travel through a wormhole in space to ensure humanity's survival.\",\n  \"releaseYear\": 2014,\n  \"duration\": 169,\n  \"genre\": \"SCIFI\",\n  \"category\": \"MOVIE\",\n  \"rating\": 8.6\n}"
			},
			"parameters": [],
			"headers": [
				{
					"name": "Content-Type",
					"value": "application/json"
				}
			],
			"authentication": {},
			"metaSortKey": -1710338000000,
			"isPrivate": false,
			"settingStoreCookies": true,
			"settingSendCookies": true,
			"settingDisableRenderRequestBody": false,
			"settingEncodeUrl": true,
			"settingRebuildPath": true,
			"settingFollowRedirects": "global"
		},
		{
			"_id": "req_list_media",
			"_type": "request",
			"parentId": "fld_media_1",
			"modified": 1710340000000,
			"created": 1710340000000,
			"url": "{{ _.base_url }}/api/v1/media",
			"name": "List All Media",
			"description": "",
			"method": "GET",
			"body": {},
			"parameters": [],
			"headers": [],
			"authentication": {},
			"metaSortKey": -1710337000000,
			"isPrivate": false,
			"settingStoreCookies": true,
			"settingSendCookies": true,
			"settingDisableRenderRequestBody": false,
			"settingEncodeUrl": true,
			"settingRebuildPath": true,
			"settingFollowRedirects": "global"
		},
		{
			"_id": "fld_sub_1",
			"_type": "request_group",
			"parentId": "wrk_mediahub_1",
			"modified": 1710340000000,
			"created": 1710340000000,
			"name": "Subscription Service",
			"description": "",
			"environment": {},
			"environmentPropertyOrder": null,
			"metaSortKey": -1710335000000
		},
		{
			"_id": "req_create_sub",
			"_type": "request",
			"parentId": "fld_sub_1",
			"modified": 1710340000000,
			"created": 1710340000000,
			"url": "{{ _.base_url }}/api/v1/subscriptions",
			"name": "Create Subscription",
			"description": "Requires a valid User ID from User Service.",
			"method": "POST",
			"body": {
				"mimeType": "application/json",
				"text": "{\n  \"userId\": 1,\n  \"planType\": \"PREMIUM\",\n  \"price\": 14.99,\n  \"startDate\": \"2024-03-13T00:00:00\",\n  \"endDate\": \"2025-03-13T00:00:00\"\n}"
			},
			"parameters": [],
			"headers": [
				{
					"name": "Content-Type",
					"value": "application/json"
				}
			],
			"authentication": {},
			"metaSortKey": -1710335000000,
			"isPrivate": false,
			"settingStoreCookies": true,
			"settingSendCookies": true,
			"settingDisableRenderRequestBody": false,
			"settingEncodeUrl": true,
			"settingRebuildPath": true,
			"settingFollowRedirects": "global"
		},
		{
			"_id": "req_media_info",
			"_type": "request",
			"parentId": "fld_sub_1",
			"modified": 1710340000000,
			"created": 1710340000000,
			"url": "{{ _.base_url }}/api/v1/subscriptions/media-info/1",
			"name": "Get Media Info (Via WebClient)",
			"description": "Subscription Service calls Media Service using WebClient.",
			"method": "GET",
			"body": {},
			"parameters": [],
			"headers": [],
			"authentication": {},
			"metaSortKey": -1710334000000,
			"isPrivate": false,
			"settingStoreCookies": true,
			"settingSendCookies": true,
			"settingDisableRenderRequestBody": false,
			"settingEncodeUrl": true,
			"settingRebuildPath": true,
			"settingFollowRedirects": "global"
		},
		{
			"_id": "fld_infra_1",
			"_type": "request_group",
			"parentId": "wrk_mediahub_1",
			"modified": 1710340000000,
			"created": 1710340000000,
			"name": "Infrastructure",
			"description": "",
			"environment": {},
			"environmentPropertyOrder": null,
			"metaSortKey": -1710320000000
		},
		{
			"_id": "req_gateway_routes",
			"_type": "request",
			"parentId": "fld_infra_1",
			"modified": 1710340000000,
			"created": 1710340000000,
			"url": "{{ _.base_url }}/actuator/gateway/routes",
			"name": "Gateway Routes",
			"description": "",
			"method": "GET",
			"body": {},
			"parameters": [],
			"headers": [],
			"authentication": {},
			"metaSortKey": -1710320000000,
			"isPrivate": false,
			"settingStoreCookies": true,
			"settingSendCookies": true,
			"settingDisableRenderRequestBody": false,
			"settingEncodeUrl": true,
			"settingRebuildPath": true,
			"settingFollowRedirects": "global"
		},
		{
			"_id": "req_eureka_status",
			"_type": "request",
			"parentId": "fld_infra_1",
			"modified": 1710340000000,
			"created": 1710340000000,
			"url": "{{ _.eureka_url }}",
			"name": "Eureka Dashboard",
			"description": "",
			"method": "GET",
			"body": {},
			"parameters": [],
			"headers": [],
			"authentication": {},
			"metaSortKey": -1710310000000,
			"isPrivate": false,
			"settingStoreCookies": true,
			"settingSendCookies": true,
			"settingDisableRenderRequestBody": false,
			"settingEncodeUrl": true,
			"settingRebuildPath": true,
			"settingFollowRedirects": "global"
		}
	]
}
